LICENSE
README.md
requirements.txt
setup.py
strymread_lite/DBC_Read_Tools.py
strymread_lite/__init__.py
strymread_lite/strymread_lite.py
strymread_lite/version
strymread_lite.egg-info/PKG-INFO
strymread_lite.egg-info/SOURCES.txt
strymread_lite.egg-info/dependency_links.txt
strymread_lite.egg-info/not-zip-safe
strymread_lite.egg-info/requires.txt
strymread_lite.egg-info/top_level.txt
strymread_lite/dbc/honda_pilot_2017.dbc
strymread_lite/dbc/nissan_rogue_2021.dbc
strymread_lite/dbc/nissan_rogue_experimental.dbc
strymread_lite/dbc/toyota_rav4_2019.dbc
strymread_lite/dbc/toyota_rav4_2020.dbc
strymread_lite/dbc/toyota_rav4_2021.dbc
strymread_lite/dbc/toyota_rav4_hybrid.dbc
strymread_lite/utils/__init__.py
strymread_lite/utils/log.py